DNSPOD_Domain_Log/__init__.py
DNSPOD_Domain_Log/check_domain_log.py
dnspod_domain_log-1.0.5.dist-info/METADATA
dnspod_domain_log-1.0.5.dist-info/WHEEL
dnspod_domain_log-1.0.5.dist-info/top_level.txt
dnspod_domain_log-1.0.5.dist-info/RECORD
